{
  "project_info": {
    "project_number": "1038673526141",
    "project_id": "prabhattraders-39d7c",
    "storage_bucket": "prabhattraders-39d7c.firebasestorage.app"
  },
  "client": [
    {
      "client_info": {
        "mobilesdk_app_id": "1:1038673526141:android:4e1c2b4a65660468de6014",
        "android_client_info": {
          "package_name": "com.techwise.prabhatapp"
        }
      },
      "oauth_client": [],
      "api_key": [
        {
          "current_key": "AIzaSyBvevuTdsT9kA5_doyIOK_oquUJpGHaCuU"
        }
      ],
      "services": {
        "appinvite_service": {
          "other_platform_oauth_client": []
        }
      }
    }
  ],
  "configuration_version": "1"
}